Git_Bundle_Plus-0.9.1.data/scripts/gitarchive
Git_Bundle_Plus-0.9.1.data/scripts/gitbundleplus
gitarchive/__init__.py
gitarchive/constants.py
gitarchive/git_cmd.py
modules/__init__.py
modules/constants.py
modules/git_cmd.py
Git_Bundle_Plus-0.9.1.dist-info/LICENSE
Git_Bundle_Plus-0.9.1.dist-info/METADATA
Git_Bundle_Plus-0.9.1.dist-info/WHEEL
Git_Bundle_Plus-0.9.1.dist-info/top_level.txt
Git_Bundle_Plus-0.9.1.dist-info/RECORD
