Metadata-Version: 2.1
Name: Git-Bundle-Plus
Version: 0.9.1
Summary: Bundle a local Git project with all uncommitted changes and stashes (git bundle on steroids).
Home-page: https://github.com/an23lm/GitBundlePlus
Author: Ansèlm Joseph
Author-email: anselmjosephs@gmail.com
License: UNKNOWN
Platform: UNKNOWN
Classifier: Programming Language :: Python :: 3
Classifier: License :: OSI Approved :: MIT License
Classifier: Operating System :: OS Independent
